rl_arena/__init__.py
rl_arena/interactive.py
rl_arena/make.py
rl_arena/submission.py
rl_arena/training.py
rl_arena/version.py
rl_arena/agents/__init__.py
rl_arena/agents/random_agent.py
rl_arena/agents/rule_based_agent.py
rl_arena/core/__init__.py
rl_arena/core/agent.py
rl_arena/core/environment.py
rl_arena/core/exceptions.py
rl_arena/core/recorder.py
rl_arena/core/renderer.py
rl_arena/core/types.py
rl_arena/envs/__init__.py
rl_arena/envs/registry.py
rl_arena/envs/pong/README.md
rl_arena/envs/pong/__init__.py
rl_arena/envs/pong/config.yaml
rl_arena/envs/pong/environment.py
rl_arena/envs/pong/renderer.py
rl_arena/tools/__init__.py
rl_arena/tools/validator.py
rl_arena/utils/__init__.py
rl_arena/utils/html_template.py
rl_arena/utils/logger.py
rl_arena/utils/replay.py
rl_arena/utils/validator.py
rl_arena-0.1.2.dist-info/licenses/LICENSE
rl_arena-0.1.2.dist-info/METADATA
rl_arena-0.1.2.dist-info/WHEEL
rl_arena-0.1.2.dist-info/top_level.txt
rl_arena-0.1.2.dist-info/RECORD
