Metadata-Version: 2.4
Name: rl-arena
Version: 0.1.2
Summary: A Python library for competitive reinforcement learning environments
Home-page: https://github.com/rl-arena/rl-arena-env
Author: RL Arena Contributors
Author-email: RL Arena Contributors <kwaklloyd@gmail.com>
License: Apache-2.0
Project-URL: Homepage, https://github.com/rl-arena/rl-arena-env
Project-URL: Documentation, https://github.com/rl-arena/rl-arena-env/tree/main/docs
Project-URL: Repository, https://github.com/rl-arena/rl-arena-env
Project-URL: Bug Tracker, https://github.com/rl-arena/rl-arena-env/issues
Keywords: reinforcement-learning,multi-agent,competition,rl,ai
Classifier: Development Status :: 3 - Alpha
Classifier: Intended Audience :: Developers
Classifier: Intended Audience :: Science/Research
Classifier: License :: OSI Approved :: Apache Software License
Classifier: Programming Language :: Python :: 3
Classifier: Programming Language :: Python :: 3.8
Classifier: Programming Language :: Python :: 3.9
Classifier: Programming Language :: Python :: 3.10
Classifier: Programming Language :: Python :: 3.11
Classifier: Topic :: Scientific/Engineering :: Artificial Intelligence
Requires-Python: >=3.9
License-File: LICENSE
Requires-Dist: numpy>=1.20.0
Requires-Dist: gymnasium>=0.28.0
Requires-Dist: pyyaml>=6.0
Provides-Extra: dev
Requires-Dist: pytest>=7.0.0; extra == "dev"
Requires-Dist: black>=22.0.0; extra == "dev"
Requires-Dist: mypy>=0.990; extra == "dev"
Requires-Dist: flake8>=5.0.0; extra == "dev"
Provides-Extra: examples
Requires-Dist: stable-baselines3>=2.0.0; extra == "examples"
Requires-Dist: matplotlib>=3.5.0; extra == "examples"
Dynamic: author
Dynamic: home-page
Dynamic: license-file
Dynamic: requires-python
